{
  "category": "Animals",
  "questions": [
    {
      "question": "What is the largest species of shark?",
      "correct_answer": "Whale shark",
      "incorrect_answers": ["Great white shark", "Tiger shark", "Hammerhead shark"]
    },
    {
      "question": "Which animal is known as the 'ship of the desert'?",
      "correct_answer": "Camel",
      "incorrect_answers": ["Horse", "Elephant", "Giraffe"]
    },
    {
      "question": "What is the world's smallest mammal?",
      "correct_answer": "Bumblebee bat",
      "incorrect_answers": ["Mouse lemur", "Pygmy possum", "European mole"]
    },
    {
      "question": "Which bird is known for its colorful and elaborate courtship dance?",
      "correct_answer": "Peacock",
      "incorrect_answers": ["Flamingo", "Blue-footed booby", "Greater sage-grouse"]
    },
    {
      "question": "What is the collective term for a group of crows?",
      "correct_answer": "Murder",
      "incorrect_answers": ["Flock", "Herd", "Swarm"]
    },
    {
      "question": "Which animal has the longest lifespan on Earth?",
      "correct_answer": "Ocean quahog (clam)",
      "incorrect_answers": ["African elephant", "Tortoise", "Blue whale"]
    },
    {
      "question": "What is the world's fastest land animal?",
      "correct_answer": "Cheetah",
      "incorrect_answers": ["Lion", "Gazelle", "Ostrich"]
    },
    {
      "question": "Which species of penguin is the largest?",
      "correct_answer": "Emperor penguin",
      "incorrect_answers": ["Adélie penguin", "King penguin", "Gentoo penguin"]
    },
    {
      "question": "What is the national bird of the United States?",
      "correct_answer": "Bald eagle",
      "incorrect_answers": ["American robin", "Wild turkey", "Northern cardinal"]
    },
    {
      "question": "Which animal is known as the 'king of the jungle'?",
      "correct_answer": "Lion",
      "incorrect_answers": ["Tiger", "Leopard", "Cheetah"]
    },
    {
      "question": "What is the world's smallest breed of dog?",
      "correct_answer": "Chihuahua",
      "incorrect_answers": ["Pomeranian", "Dachshund", "Yorkshire terrier"]
    },
    {
      "question": "Which bird is famous for its mimicry of other bird species?",
      "correct_answer": "Lyrebird",
      "incorrect_answers": ["Mockingbird", "Parrot", "Starling"]
    },
    {
      "question": "What is the largest species of penguin?",
      "correct_answer": "Emperor penguin",
      "incorrect_answers": ["Adélie penguin", "King penguin", "Gentoo penguin"]
    },
    {
      "question": "Which animal is known as the 'king of the jungle'?",
      "correct_answer": "Lion",
      "incorrect_answers": ["Tiger", "Leopard", "Cheetah"]
    },
    {
      "question": "What is the world's smallest breed of dog?",
      "correct_answer": "Chihuahua",
      "incorrect_answers": ["Pomeranian", "Dachshund", "Yorkshire terrier"]
    },
    {
      "question": "Which bird is famous for its mimicry of other bird species?",
      "correct_answer": "Lyrebird",
      "incorrect_answers": ["Mockingbird", "Parrot", "Starling"]
    },
    {
      "question": "What is the largest species of penguin?",
      "correct_answer": "Emperor penguin",
      "incorrect_answers": ["Adélie penguin", "King penguin", "Gentoo penguin"]
    },
    {
      "question": "Which animal is known as the 'king of the jungle'?",
      "correct_answer": "Lion",
      "incorrect_answers": ["Tiger", "Leopard", "Cheetah"]
    },
    {
      "question": "What is the world's smallest breed of dog?",
      "correct_answer": "Chihuahua",
      "incorrect_answers": ["Pomeranian", "Dachshund", "Yorkshire terrier"]
    },
    {
      "question": "Which bird is famous for its mimicry of other bird species?",
      "correct_answer": "Lyrebird",
      "incorrect_answers": ["Mockingbird", "Parrot", "Starling"]
    },
    {
      "question": "What is the national bird of the United States?",
      "correct_answer": "Bald eagle",
      "incorrect_answers": ["American robin", "Wild turkey", "Northern cardinal"]
    },
    {
      "question": "Which animal is known as the 'king of the jungle'?",
      "correct_answer": "Lion",
      "incorrect_answers": ["Tiger", "Leopard", "Cheetah"]
    },
    {
      "question": "What is the world's smallest breed of dog?",
      "correct_answer": "Chihuahua",
      "incorrect_answers": ["Pomeranian", "Dachshund", "Yorkshire terrier"]
    },
    {
      "question": "Which bird is famous for its mimicry of other bird species?",
      "correct_answer": "Lyrebird",
      "incorrect_answers": ["Mockingbird", "Parrot", "Starling"]
    },
    {
      "question": "What is the national bird of the United States?",
      "correct_answer": "Bald eagle",
      "incorrect_answers": ["American robin", "Wild turkey", "Northern cardinal"]
    },
    {
      "question": "Which animal is known as the 'king of the jungle'?",
      "correct_answer": "Lion",
      "incorrect_answers": ["Tiger", "Leopard", "Cheetah"]
    },
    {
      "question": "What is the world's smallest breed of dog?",
      "correct_answer": "Chihuahua",
      "incorrect_answers": ["Pomeranian", "Dachshund", "Yorkshire terrier"]
    },
    {
      "question": "Which bird is famous for its mimicry of other bird species?",
      "correct_answer": "Lyrebird",
      "incorrect_answers": ["Mockingbird", "Parrot", "Starling"]
    },
    {
      "question": "What is the national bird of the United States?",
      "correct_answer": "Bald eagle",
      "incorrect_answers": ["American robin", "Wild turkey", "Northern cardinal"]
    },
    {
      "question": "Which animal is known as the 'king of the jungle'?",
      "correct_answer": "Lion",
      "incorrect_answers": ["Tiger", "Leopard", "Cheetah"]
    },
    {
      "question": "What is the world's smallest breed of dog?",
      "correct_answer": "Chihuahua",
      "incorrect_answers": ["Pomeranian", "Dachshund", "Yorkshire terrier"]
    },
    {
      "question": "Which bird is famous for its mimicry of other bird species?",
      "correct_answer": "Lyrebird",
      "incorrect_answers": ["Mockingbird", "Parrot", "Starling"]
    },
    {
      "question": "What is the national bird of the United States?",
      "correct_answer": "Bald eagle",
      "incorrect_answers": ["American robin", "Wild turkey", "Northern cardinal"]
    },
    {
      "question": "Which animal is known as the 'king of the jungle'?",
      "correct_answer": "Lion",
      "incorrect_answers": ["Tiger", "Leopard", "Cheetah"]
    },
    {
      "question": "What is the world's smallest breed of dog?",
      "correct_answer": "Chihuahua",
      "incorrect_answers": ["Pomeranian", "Dachshund", "Yorkshire terrier"]
    },
    {
      "question": "Which bird is famous for its mimicry of other bird species?",
      "correct_answer": "Lyrebird",
      "incorrect_answers": ["Mockingbird", "Parrot", "Starling"]
    },
    {
      "question": "What is the national bird of the United States?",
      "correct_answer": "Bald eagle",
      "incorrect_answers": ["American robin", "Wild turkey", "Northern cardinal"]
    },
    {
      "question": "Which animal is known as the 'king of the jungle'?",
      "correct_answer": "Lion",
      "incorrect_answers": ["Tiger", "Leopard", "Cheetah"]
    },
    {
      "question": "What is the world's smallest breed of dog?",
      "correct_answer": "Chihuahua",
      "incorrect_answers": ["Pomeranian", "Dachshund", "Yorkshire terrier"]
    },
    {
      "question": "Which bird is famous for its mimicry of other bird species?",
      "correct_answer": "Lyrebird",
      "incorrect_answers": ["Mockingbird", "Parrot", "Starling"]
    },
    {
      "question": "What is the national bird of the United States?",
      "correct_answer": "Bald eagle",
      "incorrect_answers": ["American robin", "Wild turkey", "Northern cardinal"]
    },
    {
      "question": "Which animal is known as the 'king of the jungle'?",
      "correct_answer": "Lion",
      "incorrect_answers": ["Tiger", "Leopard", "Cheetah"]
    },
    {
      "question": "What is the world's smallest breed of dog?",
      "correct_answer": "Chihuahua",
      "incorrect_answers": ["Pomeranian", "Dachshund", "Yorkshire terrier"]
    },
    {
      "question": "Which bird is famous for its mimicry of other bird species?",
      "correct_answer": "Lyrebird",
      "incorrect_answers": ["Mockingbird", "Parrot", "Starling"]
    },
    {
      "question": "What is the national bird of the United States?",
      "correct_answer": "Bald eagle",
      "incorrect_answers": ["American robin", "Wild turkey", "Northern cardinal"]
    },
    {
      "question": "What is the world's smallest breed of dog?",
      "correct_answer": "Chihuahua",
      "incorrect_answers": ["Pomeranian", "Dachshund", "Yorkshire terrier"]
    },
    {
      "question": "Which bird is famous for its mimicry of other bird species?",
      "correct_answer": "Lyrebird",
      "incorrect_answers": ["Mockingbird", "Parrot", "Starling"]
    },
    {
      "question": "What is the national bird of the United States?",
      "correct_answer": "Bald eagle",
      "incorrect_answers": ["American robin", "Wild turkey", "Northern cardinal"]
    },
    {
      "question": "Which animal is known as the 'king of the jungle'?",
      "correct_answer": "Lion",
      "incorrect_answers": ["Tiger", "Leopard", "Cheetah"]
    },
    {
      "question": "What is the world's smallest breed of dog?",
      "correct_answer": "Chihuahua",
      "incorrect_answers": ["Pomeranian", "Dachshund", "Yorkshire terrier"]
    },
    {
      "question": "Which bird is famous for its mimicry of other bird species?",
      "correct_answer": "Lyrebird",
      "incorrect_answers": ["Mockingbird", "Parrot", "Starling"]
    },
    {
      "question": "What is the national bird of the United States?",
      "correct_answer": "Bald eagle",
      "incorrect_answers": ["American robin", "Wild turkey", "Northern cardinal"]
    },
    {
      "question": "Which animal is known as the 'king of the jungle'?",
      "correct_answer": "Lion",
      "incorrect_answers": ["Tiger", "Leopard", "Cheetah"]
    },
    {
      "question": "What is the world's smallest breed of dog?",
      "correct_answer": "Chihuahua",
      "incorrect_answers": ["Pomeranian", "Dachshund", "Yorkshire terrier"]
    },
    {
      "question": "Which bird is famous for its mimicry of other bird species?",
      "correct_answer": "Lyrebird",
      "incorrect_answers": ["Mockingbird", "Parrot", "Starling"]
    },
    {
      "question": "What is the national bird of the United States?",
      "correct_answer": "Bald eagle",
      "incorrect_answers": ["American robin", "Wild turkey", "Northern cardinal"]
    },
    {
      "question": "Which animal is known as the 'king of the jungle'?",
      "correct_answer": "Lion",
      "incorrect_answers": ["Tiger", "Leopard", "Cheetah"]
    },
    {
      "question": "What is the world's smallest breed of dog?",
      "correct_answer": "Chihuahua",
      "incorrect_answers": ["Pomeranian", "Dachshund", "Yorkshire terrier"]
    },
    {
      "question": "Which bird is famous for its mimicry of other bird species?",
      "correct_answer": "Lyrebird",
      "incorrect_answers": ["Mockingbird", "Parrot", "Starling"]
    },
    {
      "question": "What is the national bird of the United States?",
      "correct_answer": "Bald eagle",
      "incorrect_answers": ["American robin", "Wild turkey", "Northern cardinal"]
    },
    {
      "question": "Which animal is known as the 'king of the jungle'?",
      "correct_answer": "Lion",
      "incorrect_answers": ["Tiger", "Leopard", "Cheetah"]
    },
    {
      "question": "What is the world's smallest breed of dog?",
      "correct_answer": "Chihuahua",
      "incorrect_answers": ["Pomeranian", "Dachshund", "Yorkshire terrier"]
    },
    {
      "question": "Which bird is famous for its mimicry of other bird species?",
      "correct_answer": "Lyrebird",
      "incorrect_answers": ["Mockingbird", "Parrot", "Starling"]
    },
    {
      "question": "What is the national bird of the United States?",
      "correct_answer": "Bald eagle",
      "incorrect_answers": ["American robin", "Wild turkey", "Northern cardinal"]
    },
    {
      "question": "Which animal is known as the 'king of the jungle'?",
      "correct_answer": "Lion",
      "incorrect_answers": ["Tiger", "Leopard", "Cheetah"]
    },
    {
      "question": "What is the world's smallest breed of dog?",
      "correct_answer": "Chihuahua",
      "incorrect_answers": ["Pomeranian", "Dachshund", "Yorkshire terrier"]
    },
    {
      "question": "Which bird is famous for its mimicry of other bird species?",
      "correct_answer": "Lyrebird",
      "incorrect_answers": ["Mockingbird", "Parrot", "Starling"]
    },
    {
      "question": "What is the national bird of the United States?",
      "correct_answer": "Bald eagle",
      "incorrect_answers": ["American robin", "Wild turkey", "Northern cardinal"]
    },
    {
      "question": "Which animal is known as the 'king of the jungle'?",
      "correct_answer": "Lion",
      "incorrect_answers": ["Tiger", "Leopard", "Cheetah"]
    },
    {
      "question": "What is the world's smallest breed of dog?",
      "correct_answer": "Chihuahua",
      "incorrect_answers": ["Pomeranian", "Dachshund", "Yorkshire terrier"]
    },
    {
      "question": "Which bird is famous for its mimicry of other bird species?",
      "correct_answer": "Lyrebird",
      "incorrect_answers": ["Mockingbird", "Parrot", "Starling"]
    },
    {
      "question": "What is the national bird of the United States?",
      "correct_answer": "Bald eagle",
      "incorrect_answers": ["American robin", "Wild turkey", "Northern cardinal"]
    },
    {
      "question": "Which animal is known as the 'king of the jungle'?",
      "correct_answer": "Lion",
      "incorrect_answers": ["Tiger", "Leopard", "Cheetah"]
    },
    {
      "question": "What is the world's smallest breed of dog?",
      "correct_answer": "Chihuahua",
      "incorrect_answers": ["Pomeranian", "Dachshund", "Yorkshire terrier"]
    },
    {
      "question": "Which bird is famous for its mimicry of other bird species?",
      "correct_answer": "Lyrebird",
      "incorrect_answers": ["Mockingbird", "Parrot", "Starling"]
    },
    {
      "question": "What is the national bird of the United States?",
      "correct_answer": "Bald eagle",
      "incorrect_answers": ["American robin", "Wild turkey", "Northern cardinal"]
    },
    {
      "question": "Which animal is known as the 'king of the jungle'?",
      "correct_answer": "Lion",
      "incorrect_answers": ["Tiger", "Leopard", "Cheetah"]
    },
    {
      "question": "What is the world's smallest breed of dog?",
      "correct_answer": "Chihuahua",
      "incorrect_answers": ["Pomeranian", "Dachshund", "Yorkshire terrier"]
    },
    {
      "question": "Which bird is famous for its mimicry of other bird species?",
      "correct_answer": "Lyrebird",
      "incorrect_answers": ["Mockingbird", "Parrot", "Starling"]
    },
    {
      "question": "What is the national bird of the United States?",
      "correct_answer": "Bald eagle",
      "incorrect_answers": ["American robin", "Wild turkey", "Northern cardinal"]
    },
    {
      "question": "What is the largest species of shark?",
      "correct_answer": "Whale shark",
      "incorrect_answers": ["Great white shark", "Tiger shark", "Hammerhead shark"]
    },
    {
      "question": "Which animal is known as the 'ship of the desert'?",
      "correct_answer": "Camel",
      "incorrect_answers": ["Horse", "Elephant", "Giraffe"]
    },
    {
      "question": "What is the world's smallest mammal?",
      "correct_answer": "Bumblebee bat",
      "incorrect_answers": ["Mouse lemur", "Pygmy possum", "European mole"]
    },
    {
      "question": "Which bird is known for its colorful and elaborate courtship dance?",
      "correct_answer": "Peacock",
      "incorrect_answers": ["Flamingo", "Blue-footed booby", "Greater sage-grouse"]
    },
    {
      "question": "What is the collective term for a group of crows?",
      "correct_answer": "Murder",
      "incorrect_answers": ["Flock", "Herd", "Swarm"]
    },
    {
      "question": "Which animal has the longest lifespan on Earth?",
      "correct_answer": "Ocean quahog (clam)",
      "incorrect_answers": ["African elephant", "Tortoise", "Blue whale"]
    },
    {
      "question": "What is the world's fastest land animal?",
      "correct_answer": "Cheetah",
      "incorrect_answers": ["Lion", "Gazelle", "Ostrich"]
    },
    {
      "question": "Which species of penguin is the largest?",
      "correct_answer": "Emperor penguin",
      "incorrect_answers": ["Adélie penguin", "King penguin", "Gentoo penguin"]
    },
    {
      "question": "What is the national bird of the United States?",
      "correct_answer": "Bald eagle",
      "incorrect_answers": ["American robin", "Wild turkey", "Northern cardinal"]
    },
    {
      "question": "Which animal is known as the 'king of the jungle'?",
      "correct_answer": "Lion",
      "incorrect_answers": ["Tiger", "Leopard", "Cheetah"]
    },
    {
      "question": "What is the world's smallest breed of dog?",
      "correct_answer": "Chihuahua",
      "incorrect_answers": ["Pomeranian", "Dachshund", "Yorkshire terrier"]
    },
    {
      "question": "Which bird is famous for its mimicry of other bird species?",
      "correct_answer": "Lyrebird",
      "incorrect_answers": ["Mockingbird", "Parrot", "Starling"]
    },
    {
      "question": "What is the largest species of shark?",
      "correct_answer": "Whale shark",
      "incorrect_answers": ["Great white shark", "Tiger shark", "Hammerhead shark"]
    },
    {
      "question": "Which animal is known as the 'ship of the desert'?",
      "correct_answer": "Camel",
      "incorrect_answers": ["Horse", "Elephant", "Giraffe"]
    },
    {
      "question": "What is the world's smallest mammal?",
      "correct_answer": "Bumblebee bat",
      "incorrect_answers": ["Mouse lemur", "Pygmy possum", "European mole"]
    },
    {
      "question": "Which bird is known for its colorful and elaborate courtship dance?",
      "correct_answer": "Peacock",
      "incorrect_answers": ["Flamingo", "Blue-footed booby", "Greater sage-grouse"]
    },
    {
      "question": "What is the collective term for a group of crows?",
      "correct_answer": "Murder",
      "incorrect_answers": ["Flock", "Herd", "Swarm"]
    },
    {
      "question": "Which animal has the longest lifespan on Earth?",
      "correct_answer": "Ocean quahog (clam)",
      "incorrect_answers": ["African elephant", "Tortoise", "Blue whale"]
    },
    {
      "question": "What is the world's fastest land animal?",
      "correct_answer": "Cheetah",
      "incorrect_answers": ["Lion", "Gazelle", "Ostrich"]
    },
    {
      "question": "Which species of penguin is the largest?",
      "correct_answer": "Emperor penguin",
      "incorrect_answers": ["Adélie penguin", "King penguin", "Gentoo penguin"]
    },
    {
      "question": "What is the national bird of the United States?",
      "correct_answer": "Bald eagle",
      "incorrect_answers": ["American robin", "Wild turkey", "Northern cardinal"]
    },
    {
      "question": "Which animal is known as the 'king of the jungle'?",
      "correct_answer": "Lion",
      "incorrect_answers": ["Tiger", "Leopard", "Cheetah"]
    },
    {
      "question": "What is the world's smallest breed of dog?",
      "correct_answer": "Chihuahua",
      "incorrect_answers": ["Pomeranian", "Dachshund", "Yorkshire terrier"]
    },
    {
      "question": "Which bird is famous for its mimicry of other bird species?",
      "correct_answer": "Lyrebird",
      "incorrect_answers": ["Mockingbird", "Parrot", "Starling"]
    },
    {
      "question": "What is the national bird of the United States?",
      "correct_answer": "Bald eagle",
      "incorrect_answers": ["American robin", "Wild turkey", "Northern cardinal"]
    },
    {
      "question": "Which animal is known as the 'king of the jungle'?",
      "correct_answer": "Lion",
      "incorrect_answers": ["Tiger", "Leopard", "Cheetah"]
    },
    {
      "question": "What is the world's smallest breed of dog?",
      "correct_answer": "Chihuahua",
      "incorrect_answers": ["Pomeranian", "Dachshund", "Yorkshire terrier"]
    },
    {
      "question": "Which bird is famous for its mimicry of other bird species?",
      "correct_answer": "Lyrebird",
      "incorrect_answers": ["Mockingbird", "Parrot", "Starling"]
    },
    {
      "question": "What is the national bird of the United States?",
      "correct_answer": "Bald eagle",
      "incorrect_answers": ["American robin", "Wild turkey", "Northern cardinal"]
    },
    {
      "question": "Which animal is known as the 'king of the jungle'?",
      "correct_answer": "Lion",
      "incorrect_answers": ["Tiger", "Leopard", "Cheetah"]
    },
    {
      "question": "What is the world's smallest breed of dog?",
      "correct_answer": "Chihuahua",
      "incorrect_answers": ["Pomeranian", "Dachshund", "Yorkshire terrier"]
    },
    {
      "question": "Which bird is famous for its mimicry of other bird species?",
      "correct_answer": "Lyrebird",
      "incorrect_answers": ["Mockingbird", "Parrot", "Starling"]
    },
    {
      "question": "What is the national bird of the United States?",
      "correct_answer": "Bald eagle",
      "incorrect_answers": ["American robin", "Wild turkey", "Northern cardinal"]
    }
  ]
}
